icinga_pusher/__init__.py
icinga_pusher-0.1.12.dist-info/LICENSE
icinga_pusher-0.1.12.dist-info/METADATA
icinga_pusher-0.1.12.dist-info/WHEEL
icinga_pusher-0.1.12.dist-info/RECORD
